stickbugml/__init__.py
stickbugml/_util.py
stickbugml/base.py
stickbugml/decorators.py
stickbugml/singleton.py
stickbugml-1.0.4.dist-info/DESCRIPTION.rst
stickbugml-1.0.4.dist-info/METADATA
stickbugml-1.0.4.dist-info/RECORD
stickbugml-1.0.4.dist-info/WHEEL
stickbugml-1.0.4.dist-info/metadata.json
stickbugml-1.0.4.dist-info/top_level.txt
